csvai/__init__.py
csvai/__main__.py
csvai/cli.py
csvai/io_utils.py
csvai/launch.py
csvai/processor.py
csvai/settings.py
csvai/ui.py
csvai-0.2.1.dist-info/licenses/LICENSE
csvai-0.2.1.dist-info/METADATA
csvai-0.2.1.dist-info/WHEEL
csvai-0.2.1.dist-info/entry_points.txt
csvai-0.2.1.dist-info/top_level.txt
csvai-0.2.1.dist-info/RECORD
