Metadata-Version: 2.4
Name: csvai
Version: 0.2.1
Summary: Enrich CSV or Excel rows using OpenAI models (text or image analysis).
Author: Zyxware Technologies, Vimal Joseph
License-Expression: GPL-2.0-only
Project-URL: Homepage, https://www.zyxware.com/article/6935/csvai-automate-data-enrichment-any-csv-or-excel-file-generative-ai
Project-URL: Bug Tracker, https://github.com/zyxware/csvai/issues
Project-URL: Source, https://github.com/zyxware/csvai
Project-URL: Contact, https://www.zyxware.com/contact-us
Keywords: csv,excel,ai,openai,data enrichment,llm,automation,vision,image analysis
Classifier: Programming Language :: Python :: 3
Classifier: Operating System :: OS Independent
Requires-Python: >=3.9
License-File: LICENSE
Requires-Dist: openai>=1.99.0
Requires-Dist: jinja2>=3.1.4
Requires-Dist: python-dotenv>=1.0.1
Requires-Dist: pandas>=2.0.0
Requires-Dist: openpyxl>=3.1.0
Provides-Extra: ui
Requires-Dist: streamlit; extra == "ui"
Dynamic: license-file
